cci/__init__.py
cci/app.py
cci/cli.py
cci/config.py
cci/filters.py
cci/logger.py
cci/merger.py
cci/models.py
cci/net.py
cci/proxy.py
cci/server.py
cci/splitter.py
cci/storage.py
cci/watch.py
llm_interceptor/__init__.py
llm_interceptor/cli.py
llm_interceptor-2.3.1.dist-info/METADATA
llm_interceptor-2.3.1.dist-info/WHEEL
llm_interceptor-2.3.1.dist-info/entry_points.txt
llm_interceptor-2.3.1.dist-info/RECORD
