Metadata-Version: 2.4
Name: llm-interceptor
Version: 2.3.1
Summary: Intercept and analyze LLM traffic from AI coding tools
Project-URL: Homepage, https://github.com/chouzz/llm-interceptor
Project-URL: Documentation, https://github.com/chouzz/llm-interceptor#readme
Project-URL: Repository, https://github.com/chouzz/llm-interceptor
Project-URL: Issues, https://github.com/chouzz/llm-interceptor/issues
Author: chouzz
License: MIT
Keywords: agent,ai,debugging,inspect,intercept,llm,mitmproxy,observe,proxy,trace
Classifier: Development Status :: 4 - Beta
Classifier: Environment :: Console
Classifier: Intended Audience :: Developers
Classifier: License :: OSI Approved :: MIT License
Classifier: Operating System :: OS Independent
Classifier: Programming Language :: Python :: 3
Classifier: Programming Language :: Python :: 3.10
Classifier: Programming Language :: Python :: 3.11
Classifier: Programming Language :: Python :: 3.12
Classifier: Topic :: Internet :: Proxy Servers
Classifier: Topic :: Software Development :: Debuggers
Requires-Python: >=3.10
Requires-Dist: click>=8.0.0
Requires-Dist: fastapi>=0.109.0
Requires-Dist: mitmproxy>=10.0.0
Requires-Dist: pydantic>=2.0.0
Requires-Dist: python-multipart>=0.0.9
Requires-Dist: pyyaml>=6.0.0
Requires-Dist: rich>=13.0.0
Requires-Dist: tomli>=2.0.0; python_version < '3.11'
Requires-Dist: uvicorn>=0.27.0
Requires-Dist: watchdog>=4.0.0
Provides-Extra: dev
Requires-Dist: mypy>=1.0.0; extra == 'dev'
Requires-Dist: pre-commit>=3.5.0; extra == 'dev'
Requires-Dist: pytest-asyncio>=0.21.0; extra == 'dev'
Requires-Dist: pytest>=7.0.0; extra == 'dev'
Requires-Dist: ruff>=0.1.0; extra == 'dev'
